Verilog/xor.v
module xor_gate(a,b,y);
    input a,b;
    output y;
    assign y = (a&~b)|(~a&b);
endmodule

Verilog/adder.v
module full_adder(A,B,C,S,X);
  input A,B,C;
  output S,X;
  wire D,E,G,F;
  xor_gate f1 (.a(A), .b(B), .y(D));
  xor_gate f2 (.a(D), .b(C), .y(S));
  assign E = A&B;
  xor_gate f3 (.a(A), .b(B), .y(G));
  assign F = G&C;
  assign X = F|E;
endmodule

Verilog/four_bit.v
module four_bit_adder(A, B, C, S, X);
 input [3:0] A , B ;
 input C;
 output [3:0] S;
 output X;
 wire c1 , c2 ,c3 ;
 full_adder f1 (.A(A[0]), .B(B[0]), .C(C), .S(S[0]), .X(c1));
 full_adder f2 (.A(A[1]), .B(B[1]), .C(c1), .S(S[1]), .X(c2));
 full_adder f3 (.A(A[2]), .B(B[2]), .C(c2), .S(S[2]), .X(c3));
 full_adder f4 (.A(A[3]), .B(B[3]), .C(c3), .S(S[3]), .X(X));
 endmodule

Verilog/reg_alu.v
module reg_alu(A,B,S,Cin,F,C,clk,rst);
  input [3:0] A,B;
  input [2:0] S;
  input Cin;
  input clk ,rst;
  output reg [3:0] F;
  output reg C;
  wire [3:0] X,sum_out;
  wire Cout;
  reg [3:0] tempA , tempB ;

  xor_gate f0 (.a(A[0]), .b(B[0]), .y(X[0]));
  xor_gate f1 (.a(A[1]), .b(B[1]), .y(X[1]));
  xor_gate f2 (.a(A[2]), .b(B[2]), .y(X[2]));
  xor_gate f3 (.a(A[3]), .b(B[3]), .y(X[3]));

  always @(*) begin
   case(S) 
     3'b000: begin tempA = 4'b0000; tempB= B; end
     3'b001: begin tempA = A ;tempB = B; end
     3'b010: begin tempA = A ;tempB = ~B; end
     3'b011: begin tempA = A ;tempB = 4'b1111; end
     3'b100: begin tempA = A ;tempB = A|B; end
     3'b101: begin tempB = X; end
     3'b110: begin tempB = A&B; end
     3'b111: begin tempB = ~A; end
 endcase
     end
     four_bit_adder r1 (.A(tempA), .B(tempB), .C(Cin), .S(sum_out), .X(Cout));
 always @(posedge clk or negedge rst)begin
   if (rst) begin
     F <= (S <=3'b011) ? sum_out : tempB;
     C <= (S <=3'b011) ? Cout : 1'b0;
     end
   else begin
    F <= 4'b0000;
    C <= 1'b0;
    end
end

endmodule

Verilog/ram.v
module ram(addr,datain,csn,rwn,dataout,clk,rst);
  input [3:0] addr,datain;
  input csn , rwn ,clk ,rst;
  output reg  [3:0]  dataout;
  reg [3:0] mem [15:0];
  integer i;

  
  always@(posedge clk or negegde rst)begin
   if(!rst) begin
         for(i=0;i<16;i++) begin
            mem[i] = 4'b0000;
         end
         dataout = 4'b0000;
      end
   else  begin
      if(!csn) begin
         if(rwn) begin
            dataout <= mem[addr];
         end 
         else begin
            mem[addr] <= datain;
            dataout <= 4'bz;
         end
      end
      else begin
      dataout <= 4'bz;
      end
   end

end 
endmodule

Verilog/inst_dec.v
module inst_dec(clk,rst,inst,carry,rwn,csn,opcod,op1,op2);
   input clk ,rst ;
   input [10:0] inst ;
   output reg carry ,rwn, csn ;
   output reg [2:0] opcod ;
   output reg [3:0] op1 ,op2;
   reg [1:0] state ;

   
   parameter
     init = 2'b00  , fetch = 2'b01  , execute = 2'b10 , store = 2'b11 ;

   always @ (posedge clk or negedge rst)
   begin   
     if (!rst) begin 
        state <= init;
        op1 <= 4'b0000;
        op2 <= 4'b0000;
        opcod <= 3'b000;
        csn <= 1'b1; 

      end 

      else begin 
          case(state) 
             init : begin 
                 state <= fetch;
                 opcod <= inst[10:8];
                 op1 <= inst[7:4];
                 op2 <= inst[3:0];
                 csn <= 1'b0;
                 rwn <= 1'b1;
                 end 
             fetch : begin
                 state <= execute;
                 csn <= 1'b1;
                 if (opcod == 3'd2) begin
                     carry <= 1'b1;
                 end 
                 else begin
                     carry <= 1'b0;
                 end 
                 end
             execute : begin
                 state <= store;
                 csn <= 1'b0;
                 rwn <= 1'b0;
               end 
             store : begin 
                 state <= fetch;
                 state <= fetch;
                 opcod <= inst[10:8];
                 op1 <= inst[7:4];
                 op2 <= inst[3:0];
                 csn <= 1'b0;
                 rwn <= 1'b1;
               end 
            endcase 
         end
     end               
endmodule

Verilog/processor.v
module processor(inst, clk, rst);
   input clk , rst ;
   input [10:0] inst;
   wire carry , cout;
   wire [2:0] opcod;
   wire [3:0] op1,op2;
   wire csn , rwn ;
   wire [3:0] a;
   wire [3:0] data_alu;


   inst_dec f1 (
    .clk(clk),
    .rst(rst),
    .inst(inst),
    .opcod(opcod),
    .op1(op1),
    .op2(op2),
    .csn(csn),
    .rwn(rwn),
    .carry(carry)


   );

   ram f2(
    .addr(op1),
    .datain(data_alu),
    .csn(csn),
    .rwn(rwn),
    .dataout(a),
    .clk(clk),
    .rst(rst)
   );

reg_alu f3(
    .A(a),
    .B(op2),
    .S(opcod),
    .Cin(carry),
    .clk(clk),
    .rst(rst),
    .F(data_alu),
    .C(cout)
) ;

endmodule

Verilog/pro_tb.v
module pro_tb;
    reg clk;
    reg rst;
    reg [10:0] inst;

processor uut (
    .clk(clk),
    .rst(rst),
    .inst(inst)
);

always #10 clk = ~clk;

initial begin
    $dumpfile("prowaveform.vcd");
    $dumpvars(0, pro_tb);

    clk = 0;
    rst = 0;
    inst = 11'b00000000000;
    #10 rst = 1;

    inst = 11'b00000011000;
#60;

    inst = 11'b00100010100;
#60;

    inst = 11'b10100010011;
#60;

    $finish;
end

initial begin
    $monitor("Time=%0t | clk=%b | rst=%b | inst=%b", $time, clk, rst, inst);
end
endmodule

Verilog/prowaveform.vcd
$date
	Wed Feb 19 14:42:43 2025
$end
$version
	Icarus Verilog
$end
$timescale
	1s
$end
$scope module pro_tb $end
$var reg 1 ! clk $end
$var reg 11 " inst [10:0] $end
$var reg 1 # rst $end
$scope module uut $end
$var wire 1 ! clk $end
$var wire 11 $ inst [10:0] $end
$var wire 1 # rst $end
$var wire 1 % rwn $end
$var wire 3 & opcod [2:0] $end
$var wire 4 ' op2 [3:0] $end
$var wire 4 ( op1 [3:0] $end
$var wire 4 ) data_alu [3:0] $end
$var wire 1 * csn $end
$var wire 1 + cout $end
$var wire 1 , carry $end
$var wire 4 - a [3:0] $end
$scope module f1 $end
$var wire 1 ! clk $end
$var wire 11 . inst [10:0] $end
$var wire 1 # rst $end
$var reg 1 , carry $end
$var reg 1 * csn $end
$var reg 4 / op1 [3:0] $end
$var reg 4 0 op2 [3:0] $end
$var reg 3 1 opcod [2:0] $end
$var reg 1 % rwn $end
$var reg 2 2 state [1:0] $end
$upscope $end
$scope module f2 $end
$var wire 4 3 addr [3:0] $end
$var wire 1 ! clk $end
$var wire 1 * csn $end
$var wire 1 # rst $end
$var wire 1 % rwn $end
$var wire 4 4 datain [3:0] $end
$var reg 4 5 dataout [3:0] $end
$var integer 32 6 i [31:0] $end
$upscope $end
$scope module f3 $end
$var wire 4 7 A [3:0] $end
$var wire 4 8 B [3:0] $end
$var wire 1 , Cin $end
$var wire 3 9 S [2:0] $end
$var wire 1 ! clk $end
$var wire 1 # rst $end
$var wire 4 : sum_out [3:0] $end
$var wire 4 ; X [3:0] $end
$var wire 1 < Cout $end
$var reg 1 + C $end
$var reg 4 = F [3:0] $end
$var reg 4 > tempA [3:0] $end
$var reg 4 ? tempB [3:0] $end
$scope module f0 $end
$var wire 1 @ a $end
$var wire 1 A b $end
$var wire 1 B y $end
$upscope $end
$scope module f1 $end
$var wire 1 C a $end
$var wire 1 D b $end
$var wire 1 E y $end
$upscope $end
$scope module f2 $end
$var wire 1 F a $end
$var wire 1 G b $end
$var wire 1 H y $end
$upscope $end
$scope module f3 $end
$var wire 1 I a $end
$var wire 1 J b $end
$var wire 1 K y $end
$upscope $end
$scope module r1 $end
$var wire 4 L A [3:0] $end
$var wire 4 M B [3:0] $end
$var wire 1 , C $end
$var wire 1 N c3 $end
$var wire 1 O c2 $end
$var wire 1 P c1 $end
$var wire 1 < X $end
$var wire 4 Q S [3:0] $end
$scope module f1 $end
$var wire 1 R A $end
$var wire 1 S B $end
$var wire 1 , C $end
$var wire 1 T E $end
$var wire 1 U F $end
$var wire 1 P X $end
$var wire 1 V S $end
$var wire 1 W G $end
$var wire 1 X D $end
$scope module f1 $end
$var wire 1 R a $end
$var wire 1 S b $end
$var wire 1 X y $end
$upscope $end
$scope module f2 $end
$var wire 1 X a $end
$var wire 1 , b $end
$var wire 1 V y $end
$upscope $end
$scope module f3 $end
$var wire 1 R a $end
$var wire 1 S b $end
$var wire 1 W y $end
$upscope $end
$upscope $end
$scope module f2 $end
$var wire 1 Y A $end
$var wire 1 Z B $end
$var wire 1 P C $end
$var wire 1 [ E $end
$var wire 1 \ F $end
$var wire 1 O X $end
$var wire 1 ] S $end
$var wire 1 ^ G $end
$var wire 1 _ D $end
$scope module f1 $end
$var wire 1 Y a $end
$var wire 1 Z b $end
$var wire 1 _ y $end
$upscope $end
$scope module f2 $end
$var wire 1 _ a $end
$var wire 1 P b $end
$var wire 1 ] y $end
$upscope $end
$scope module f3 $end
$var wire 1 Y a $end
$var wire 1 Z b $end
$var wire 1 ^ y $end
$upscope $end
$upscope $end
$scope module f3 $end
$var wire 1 ` A $end
$var wire 1 a B $end
$var wire 1 O C $end
$var wire 1 b E $end
$var wire 1 c F $end
$var wire 1 N X $end
$var wire 1 d S $end
$var wire 1 e G $end
$var wire 1 f D $end
$scope module f1 $end
$var wire 1 ` a $end
$var wire 1 a b $end
$var wire 1 f y $end
$upscope $end
$scope module f2 $end
$var wire 1 f a $end
$var wire 1 O b $end
$var wire 1 d y $end
$upscope $end
$scope module f3 $end
$var wire 1 ` a $end
$var wire 1 a b $end
$var wire 1 e y $end
$upscope $end
$upscope $end
$scope module f4 $end
$var wire 1 g A $end
$var wire 1 h B $end
$var wire 1 N C $end
$var wire 1 i E $end
$var wire 1 j F $end
$var wire 1 < X $end
$var wire 1 k S $end
$var wire 1 l G $end
$var wire 1 m D $end
$scope module f1 $end
$var wire 1 g a $end
$var wire 1 h b $end
$var wire 1 m y $end
$upscope $end
$scope module f2 $end
$var wire 1 m a $end
$var wire 1 N b $end
$var wire 1 k y $end
$upscope $end
$scope module f3 $end
$var wire 1 g a $end
$var wire 1 h b $end
$var wire 1 l y $end
$upscope $end
$upscope $end
$upscope $end
$upscope $end
$upscope $end
$upscope $end
$enddefinitions $end
#0
$dumpvars
0m
0l
0k
0j
0i
0h
0g
0f
0e
0d
0c
0b
0a
0`
0_
0^
0]
0\
0[
0Z
0Y
0X
0W
xV
0U
0T
0S
0R
b0x Q
0P
0O
0N
b0 M
b0 L
xK
0J
xI
xH
0G
xF
xE
0D
xC
xB
0A
x@
b0 ?
b0 >
b0 =
0<
bx ;
b0x :
b0 9
b0 8
bx 7
bx 6
bx 5
b0 4
b0 3
b0 2
b0 1
b0 0
b0 /
b0 .
bx -
x,
0+
1*
b0 )
b0 (
b0 '
b0 &
x%
b0 $
0#
b0 "
0!
$end
#10
b100x :
b100x Q
1k
1m
1l
1h
1J
b1000 ?
b1000 M
z@
zC
zF
zI
b0x )
b0x 4
b0x =
1%
0*
b1000 '
b1000 0
b1000 8
b1 (
b1 /
b1 3
b1 2
bz -
bz 5
bz 7
b11000 "
b11000 $
b11000 .
1#
1!
#20
0!
#30
b1000 :
b1000 Q
0V
x@
xC
xF
xI
0,
1*
b10 2
b100x )
b100x 4
b100x =
bx -
bx 5
bx 7
1!
#40
0!
#50
z@
zC
zF
zI
b1000 )
b1000 4
b1000 =
0%
0*
b11 2
bz -
bz 5
bz 7
1!
#60
0!
#70
x<
xk
xj
xV
x]
bx :
bx Q
xd
xm
xl
xX
xW
x_
x^
xN
xf
xe
bx ;
xK
xb
1a
0h
zR
zY
z`
zg
1G
0J
b100 ?
b100 M
bz >
bz L
1%
b100 '
b100 0
b100 8
b1 &
b1 1
b1 9
b1 2
1!
b100010100 "
b100010100 $
b100010100 .
#80
0!
#90
1k
1d
0V
b1100 :
b1100 Q
0]
0<
1f
1e
0j
0X
0W
0_
0^
0N
1m
1l
1H
0b
0B
0E
b1100 ;
1K
0R
0Y
0`
1g
b1000 >
b1000 L
0@
0C
0F
1I
x+
bx )
bx 4
bx =
1*
b10 2
b1000 -
b1000 5
b1000 7
1!
#100
0!
#110
xd
xV
x]
bx :
bx Q
xk
x<
xf
xe
xj
xX
xW
x_
x^
xN
xm
xl
xH
xb
xB
xE
bx ;
xK
zR
zY
z`
zg
bz >
bz L
z@
zC
zF
zI
0%
0*
b11 2
0+
b1100 )
b1100 4
b1100 =
bz -
bz 5
bz 7
1!
#120
0!
#130
xb
x\
xc
xP
xO
bx ;
xH
xT
x[
xi
xS
xZ
xa
xh
1A
1D
0G
bx ?
bx M
x+
bx )
bx 4
bx =
1%
b11 '
b11 0
b11 8
b101 &
b101 1
b101 9
b1 2
1!
b10100010011 "
b10100010011 $
b10100010011 .
#140
0!
#150
1S
1Z
1a
1h
1B
1E
b1111 ?
b1111 M
1H
b1111 ;
1K
0@
0C
1F
1I
1*
b10 2
0+
b1100 -
b1100 5
b1100 7
1!
#160
0!
#170
xS
xZ
xa
xh
xB
xE
bx ?
bx M
xH
bx ;
xK
z@
zC
zF
zI
b1111 )
b1111 4
b1111 =
0%
0*
b11 2
bz -
bz 5
bz 7
1!
#180
0!
#190
1%
b1 2
bx )
bx 4
bx =
1!
