Verilog/ram.v
module ram(addr,datain,csn,rwn,dataout,clk,rst);
  input [3:0] addr,datain;
  input csn , rwn ,clk ,rst;
  output reg  [3:0]  dataout;
  reg [3:0] mem [15:0];
  integer i;

  
  always@(posedge clk or negegde rst)begin
   if(!rst) begin
         for(i=0;i<16;i++) begin
            mem[i] = 4'b0000;
         end
         dataout = 4'b0000;
      end
   else  begin
      if(!csn) begin
         if(rwn) begin
            dataout <= mem[addr];
         end 
         else begin
            mem[addr] <= datain;
            dataout <= 4'bz;
         end
      end
      else begin
      dataout <= 4'bz;
      end
   end

end 
endmodule

Verilog/ram_tb.v
module ram_tb;
 reg clk , rst;
 reg [3:0] addr,datain;
 reg csn,rwn;
 wire [3:0] dataout;

 ram uut(
    .clk(clk),
    .rst(rst),
    .addr(addr),
    .datain(datain),
    .csn(csn),
    .rwn(rwn),
    .dataout(dataout)
 );
 always #10 clk = ~clk;

 initial begin
   $dumpfile("waveform.vcd");
   $dumpvars(0,ram_tb);
   clk =0;
   rst =0;
   addr = 4'b0000;
   datain = 4'b0000;
   csn =1;
   rwn =1;
   #20 rst =1;
       
        #20 csn = 0; rwn = 0; addr = 4'b0001; datain = 4'b0010;
        #20 csn = 0; rwn = 1; addr = 4'b0001;  
        #20 csn = 0; rwn = 0; addr = 4'b0010; datain = 4'b0100;
        #20 csn = 0; rwn = 1; addr = 4'b0010;
        #20 csn = 0; rwn = 0; addr = 4'b0011; datain = 4'b0011;
        #20 csn = 0; rwn = 1; addr = 4'b0011;

        #20 csn = 1;
        #20 $finish;
    end
    initial begin
        #10;$monitor("Time: %0t | clk: %b | rst: %b | csn: %b | rwn: %b | addr: %d | datain: %d | dataout: %d", $time, clk, rst, csn, rwn, addr, datain, dataout);
    end
endmodule

Verilog/waveform.vcd
$date
	Wed Feb 19 14:57:20 2025
$end
$version
	Icarus Verilog
$end
$timescale
	1s
$end
$scope module ram_tb $end
$var wire 4 ! dataout [3:0] $end
$var reg 4 " addr [3:0] $end
$var reg 1 # clk $end
$var reg 1 $ csn $end
$var reg 4 % datain [3:0] $end
$var reg 1 & rst $end
$var reg 1 ' rwn $end
$scope module uut $end
$var wire 4 ( addr [3:0] $end
$var wire 1 # clk $end
$var wire 1 $ csn $end
$var wire 4 ) datain [3:0] $end
$var wire 1 & rst $end
$var wire 1 ' rwn $end
$var reg 4 * dataout [3:0] $end
$var integer 32 + i [31:0] $end
$upscope $end
$upscope $end
$enddefinitions $end
#0
$dumpvars
b10000 +
b0 *
b0 )
b0 (
1'
0&
b0 %
1$
0#
b0 "
b0 !
$end
#10
1#
#20
0#
1&
#30
1#
#40
0#
b10 %
b10 )
b1 "
b1 (
0'
0$
#50
1#
#60
0#
1'
#70
1#
#80
0#
b100 %
b100 )
b10 "
b10 (
0'
#90
1#
#100
0#
1'
#110
1#
#120
0#
b11 %
b11 )
b11 "
b11 (
0'
#130
1#
#140
0#
1'
#150
1#
#160
0#
1$
